ubami.py
ubami-0.1.2.dist-info/entry_points.txt
ubami-0.1.2.dist-info/LICENSE
ubami-0.1.2.dist-info/WHEEL
ubami-0.1.2.dist-info/METADATA
ubami-0.1.2.dist-info/RECORD
