Metadata-Version: 2.1
Name: ubami
Version: 0.1.2
Summary: List and find the latest Ubuntu AMIs from cloud-images.ubuntu.com.
Author-email: Chris Coleman <chris@chriscoleman.uk>
Classifier: License :: OSI Approved :: MIT License
Requires-Dist: click
Requires-Dist: httpx
